setup.py
mathcal/__init__.py
mathcal.egg-info/PKG-INFO
mathcal.egg-info/SOURCES.txt
mathcal.egg-info/dependency_links.txt
mathcal.egg-info/top_level.txt