Metadata-Version: 1.0
Name: mathcal
Version: 0.3
Summary: math calculations
Home-page: UNKNOWN
Author: jagadish
Author-email: jagadish@hgmail.com
License: MIT
Platform: UNKNOWN
